[
  {
    "rank": 1,
    "image": "leaderboardShield.png",
    "tokenAddress": "0x1111...11",
    "level": 2,
    "totalAmount": "$1,005,000.00"
  },
  {
    "rank": 2,
    "image": "leaderboardShield.png",
    "tokenAddress": "0x2222...22",
    "level": 3,
    "totalAmount": "$2,010,000.00"
  },
  {
    "rank": 3,
    "image": "leaderboardShield.png",
    "tokenAddress": "0x3333...33",
    "level": 4,
    "totalAmount": "$3,000,000.00"
  },
  {
    "rank": 4,
    "image": "leaderboardShield.png",
    "tokenAddress": "0x4444...44",
    "level": 5,
    "totalAmount": "$4,005,000.00"
  },
  {
    "rank": 5,
    "image": "leaderboardShield.png",
    "tokenAddress": "0x5555...55",
    "level": 1,
    "totalAmount": "$5,010,000.00"
  },
  {
    "rank": 6,
    "image": "leaderboardShield.png",
    "tokenAddress": "0x6666...66",
    "level": 2,
    "totalAmount": "$6,000,000.00"
  },
  {
    "rank": 7,
    "image": "leaderboardShield.png",
    "tokenAddress": "0x7777...77",
    "level": 3,
    "totalAmount": "$7,005,000.00"
  },
  {
    "rank": 8,
    "image": "leaderboardShield.png",
    "tokenAddress": "0x8888...88",
    "level": 4,
    "totalAmount": "$8,010,000.00"
  },
  {
    "rank": 9,
    "image": "leaderboardShield.png",
    "tokenAddress": "0x9999...99",
    "level": 5,
    "totalAmount": "$9,000,000.00"
  },
  {
    "rank": 10,
    "image": "leaderboardShield.png",
    "tokenAddress": "0x10101010...a10",
    "level": 1,
    "totalAmount": "$10,005,000.00"
  },
  {
    "rank": 11,
    "image": "leaderboardShield.png",
    "tokenAddress": "0x11111111...b11",
    "level": 2,
    "totalAmount": "$11,010,000.00"
  },
  {
    "rank": 12,
    "image": "leaderboardShield.png",
    "tokenAddress": "0x12121212...c12",
    "level": 3,
    "totalAmount": "$12,000,000.00"
  },
  {
    "rank": 13,
    "image": "leaderboardShield.png",
    "tokenAddress": "0x13131313...d13",
    "level": 4,
    "totalAmount": "$13,005,000.00"
  },
  {
    "rank": 14,
    "image": "leaderboardShield.png",
    "tokenAddress": "0x14141414...e14",
    "level": 5,
    "totalAmount": "$14,010,000.00"
  },
  {
    "rank": 15,
    "image": "leaderboardShield.png",
    "tokenAddress": "0x15151515...f15",
    "level": 1,
    "totalAmount": "$15,000,000.00"
  },
  {
    "rank": 16,
    "image": "leaderboardShield.png",
    "tokenAddress": "0x16161616...1016",
    "level": 2,
    "totalAmount": "$16,005,000.00"
  },
  {
    "rank": 17,
    "image": "leaderboardShield.png",
    "tokenAddress": "0x17171717...1117",
    "level": 3,
    "totalAmount": "$17,010,000.00"
  },
  {
    "rank": 18,
    "image": "leaderboardShield.png",
    "tokenAddress": "0x18181818...1218",
    "level": 4,
    "totalAmount": "$18,000,000.00"
  },
  {
    "rank": 19,
    "image": "leaderboardShield.png",
    "tokenAddress": "0x19191919...1319",
    "level": 5,
    "totalAmount": "$19,005,000.00"
  },
  {
    "rank": 20,
    "image": "leaderboardShield.png",
    "tokenAddress": "0x20202020...1420",
    "level": 1,
    "totalAmount": "$20,010,000.00"
  },
  {
    "rank": 21,
    "image": "leaderboardShield.png",
    "tokenAddress": "0x21212121...1521",
    "level": 2,
    "totalAmount": "$21,000,000.00"
  },
  {
    "rank": 22,
    "image": "leaderboardShield.png",
    "tokenAddress": "0x22222222...1622",
    "level": 3,
    "totalAmount": "$22,005,000.00"
  },
  {
    "rank": 23,
    "image": "leaderboardShield.png",
    "tokenAddress": "0x23232323...1723",
    "level": 4,
    "totalAmount": "$23,010,000.00"
  },
  {
    "rank": 24,
    "image": "leaderboardShield.png",
    "tokenAddress": "0x24242424...1824",
    "level": 5,
    "totalAmount": "$24,000,000.00"
  },
  {
    "rank": 25,
    "image": "leaderboardShield.png",
    "tokenAddress": "0x25252525...1925",
    "level": 1,
    "totalAmount": "$25,005,000.00"
  },
  {
    "rank": 26,
    "image": "leaderboardShield.png",
    "tokenAddress": "0x26262626...1a26",
    "level": 2,
    "totalAmount": "$26,010,000.00"
  },
  {
    "rank": 27,
    "image": "leaderboardShield.png",
    "tokenAddress": "0x27272727...1b27",
    "level": 3,
    "totalAmount": "$27,000,000.00"
  },
  {
    "rank": 28,
    "image": "leaderboardShield.png",
    "tokenAddress": "0x28282828...1c28",
    "level": 4,
    "totalAmount": "$28,005,000.00"
  },
  {
    "rank": 29,
    "image": "leaderboardShield.png",
    "tokenAddress": "0x29292929...1d29",
    "level": 5,
    "totalAmount": "$29,010,000.00"
  },
  {
    "rank": 30,
    "image": "leaderboardShield.png",
    "tokenAddress": "0x30303030...1e30",
    "level": 1,
    "totalAmount": "$30,000,000.00"
  }
]
